codeguard/__init__.py
codeguard/codeguard.py
codeguard-0.1.3.dist-info/METADATA
codeguard-0.1.3.dist-info/WHEEL
codeguard-0.1.3.dist-info/top_level.txt
codeguard-0.1.3.dist-info/RECORD
