Metadata-Version: 2.1
Name: codeguard
Version: 0.1.3
Summary: A utility for modifying Python scripts at runtime.
Author: Deepak Kumar
Author-email: Deepakkr455@outlook.com
